hzjwtauthenticator/__init__.py
hzjwtauthenticator/hzjwtauthenticator.py
hubzero_jupyterhub_hzjwtauthenticator-20180312164541.dist-info/LICENSE
hubzero_jupyterhub_hzjwtauthenticator-20180312164541.dist-info/METADATA
hubzero_jupyterhub_hzjwtauthenticator-20180312164541.dist-info/WHEEL
hubzero_jupyterhub_hzjwtauthenticator-20180312164541.dist-info/top_level.txt
hubzero_jupyterhub_hzjwtauthenticator-20180312164541.dist-info/RECORD
